can/__init__.py
can/_entry_points.py
can/bit_timing.py
can/broadcastmanager.py
can/bus.py
can/ctypesutil.py
can/exceptions.py
can/interface.py
can/listener.py
can/logconvert.py
can/logger.py
can/message.py
can/notifier.py
can/player.py
can/py.typed
can/thread_safe_bus.py
can/typechecking.py
can/util.py
can/viewer.py
can/interfaces/__init__.py
can/interfaces/canalystii.py
can/interfaces/cantact.py
can/interfaces/gs_usb.py
can/interfaces/iscan.py
can/interfaces/nican.py
can/interfaces/nixnet.py
can/interfaces/robotell.py
can/interfaces/slcan.py
can/interfaces/virtual.py
can/interfaces/etas/__init__.py
can/interfaces/etas/boa.py
can/interfaces/ics_neovi/__init__.py
can/interfaces/ics_neovi/neovi_bus.py
can/interfaces/ixxat/__init__.py
can/interfaces/ixxat/canlib.py
can/interfaces/ixxat/canlib_vcinpl.py
can/interfaces/ixxat/canlib_vcinpl2.py
can/interfaces/ixxat/constants.py
can/interfaces/ixxat/exceptions.py
can/interfaces/ixxat/structures.py
can/interfaces/kvaser/__init__.py
can/interfaces/kvaser/canlib.py
can/interfaces/kvaser/constants.py
can/interfaces/kvaser/structures.py
can/interfaces/neousys/__init__.py
can/interfaces/neousys/neousys.py
can/interfaces/pcan/__init__.py
can/interfaces/pcan/basic.py
can/interfaces/pcan/pcan.py
can/interfaces/seeedstudio/__init__.py
can/interfaces/seeedstudio/seeedstudio.py
can/interfaces/serial/__init__.py
can/interfaces/serial/serial_can.py
can/interfaces/socketcan/__init__.py
can/interfaces/socketcan/constants.py
can/interfaces/socketcan/socketcan.py
can/interfaces/socketcan/utils.py
can/interfaces/socketcand/__init__.py
can/interfaces/socketcand/socketcand.py
can/interfaces/systec/__init__.py
can/interfaces/systec/constants.py
can/interfaces/systec/exceptions.py
can/interfaces/systec/structures.py
can/interfaces/systec/ucan.py
can/interfaces/systec/ucanbus.py
can/interfaces/udp_multicast/__init__.py
can/interfaces/udp_multicast/bus.py
can/interfaces/udp_multicast/utils.py
can/interfaces/usb2can/__init__.py
python_can-4.4.2.dist-info/LICENSE.txt
python_can-4.4.2.dist-info/METADATA
python_can-4.4.2.dist-info/WHEEL
python_can-4.4.2.dist-info/entry_points.txt
python_can-4.4.2.dist-info/top_level.txt
python_can-4.4.2.dist-info/RECORD
