Metadata-Version: 2.1
Name: python-can
Version: 4.4.2
Summary: Controller Area Network interface module for Python
Author: python-can contributors
License: LGPL v3
Project-URL: homepage, https://github.com/hardbyte/python-can
Project-URL: documentation, https://python-can.readthedocs.io
Project-URL: repository, https://github.com/hardbyte/python-can
Project-URL: changelog, https://github.com/hardbyte/python-can/blob/develop/CHANGELOG.md
Classifier: Development Status :: 5 - Production/Stable
Classifier: Environment :: Console
Classifier: Intended Audience :: Developers
Classifier: Intended Audience :: Education
Classifier: Intended Audience :: Information Technology
Classifier: Intended Audience :: Manufacturing
Classifier: Intended Audience :: Telecommunications Industry
Classifier: License :: OSI Approved :: GNU Lesser General Public License v3 (LGPLv3)
Classifier: Natural Language :: English
Classifier: Operating System :: MacOS
Classifier: Operating System :: Microsoft :: Windows
Classifier: Operating System :: POSIX :: Linux
Classifier: Programming Language :: Python
Classifier: Programming Language :: Python :: 3.8
Classifier: Programming Language :: Python :: 3.9
Classifier: Programming Language :: Python :: 3.10
Classifier: Programming Language :: Python :: 3.11
Classifier: Programming Language :: Python :: 3.12
Classifier: Programming Language :: Python :: Implementation :: CPython
Classifier: Programming Language :: Python :: Implementation :: PyPy
Classifier: Topic :: Software Development :: Embedded Systems
Classifier: Topic :: Software Development :: Embedded Systems :: Controller Area Network (CAN)
Classifier: Topic :: System :: Hardware :: Hardware Drivers
Classifier: Topic :: System :: Logging
Classifier: Topic :: System :: Monitoring
Classifier: Topic :: System :: Networking
Classifier: Topic :: Utilities
Requires-Python: >=3.8
License-File: LICENSE.txt
Requires-Dist: wrapt~=1.10
Requires-Dist: packaging>=23.1
Requires-Dist: typing_extensions>=3.10.0.0
Requires-Dist: msgpack~=1.0.0; platform_system != "Windows"
Requires-Dist: pywin32>=305; platform_system == "Windows" and platform_python_implementation == "CPython"
Provides-Extra: lint
Requires-Dist: pylint==3.2.*; extra == "lint"
Requires-Dist: ruff==0.4.8; extra == "lint"
Requires-Dist: black==24.4.*; extra == "lint"
Requires-Dist: mypy==1.10.*; extra == "lint"
Provides-Extra: seeedstudio
Requires-Dist: pyserial>=3.0; extra == "seeedstudio"
Provides-Extra: serial
Requires-Dist: pyserial~=3.0; extra == "serial"
Provides-Extra: neovi
Requires-Dist: filelock; extra == "neovi"
Requires-Dist: python-ics>=2.12; extra == "neovi"
Provides-Extra: canalystii
Requires-Dist: canalystii>=0.1.0; extra == "canalystii"
Provides-Extra: cantact
Requires-Dist: cantact>=0.0.7; extra == "cantact"
Provides-Extra: cvector
Requires-Dist: python-can-cvector; extra == "cvector"
Provides-Extra: gs-usb
Requires-Dist: gs_usb>=0.2.1; extra == "gs-usb"
Provides-Extra: nixnet
Requires-Dist: nixnet>=0.3.2; extra == "nixnet"
Provides-Extra: pcan
Requires-Dist: uptime~=3.0.1; extra == "pcan"
Provides-Extra: remote
Requires-Dist: python-can-remote; extra == "remote"
Provides-Extra: sontheim
Requires-Dist: python-can-sontheim>=0.1.2; extra == "sontheim"
Provides-Extra: canine
Requires-Dist: python-can-canine>=0.2.2; extra == "canine"
Provides-Extra: viewer
Requires-Dist: windows-curses; (platform_system == "Windows" and platform_python_implementation == "CPython") and extra == "viewer"
Provides-Extra: mf4
Requires-Dist: asammdf>=6.0.0; extra == "mf4"
